Metadata-Version: 1.2
Name: adrianAppTeste
Version: 0.0.2
Summary: Teste
Home-page: UNKNOWN
Author: Adrian Grosch
Author-email: adriangrosch15@gmail.com
License: UNKNOWN
Platform: UNKNOWN
Requires-Python: >=3.6
